Alu.vhdl
-- Alu.vhdl
-- Author: Reinaldo Miranda de Assis
-- Date: 2023-04-17
-- Description: ALU for MIPS processor

-- Instruction	funccode/Function	
-- add 	    100000	
-- addu 	100001	
-- addi 	001000	
-- and 	    100100	
-- andi 	001100	
-- div 	    011010	
-- divu 	011011	 
-- mult 	011000	
-- multu 	011001	
-- nor 	    100111	
-- or 	    100101	
-- ori 	    001101	
-- sll 	    000000	
-- sllv 	000100	
-- sra 	    000011	
-- srav 	000111	
-- srl 	    000010	
-- srlv 	000110	
-- sub 	    100010	
-- subu 	100011	
-- xor 	    100110	
-- xori 	001110	

LIBRARY ieee;
USE ieee.std_logic_1164.ALL;
USE ieee.std_logic_unsigned.ALL;
use ieee.numeric_std.all;
USE IEEE.NUMERIC_STD.ALL;

entity alu is
    port (
        a, b : in std_logic_vector(31 downto 0);
        clk : in std_logic;
        func : in std_logic_vector(5 downto 0);
        shift : in std_logic_vector(4 downto 0);
        result : out std_logic_vector(31 downto 0); --TODO: add overflow 
        zero : out std_logic
    );
end alu;

architecture rtl of alu is
    signal a_s, b_s : signed(31 downto 0);
    signal result_s : signed(31 downto 0);

begin
    a_s <= signed(a);
    b_s <= signed(b);

    process (clk)
    begin
        -- func codes from standard MIPS instruction set
        if rising_edge(clk) then
            case func is
                when "000000" => -- sll
                    result_s <= a_s sll to_integer(unsigned(shift));
                when "000010" => -- srl
                    result_s <= a_s srl to_integer(unsigned(shift));
                when "000011" => -- sra
                    result_s <= a_s;
                when "000100" => -- sllv
                    result_s <= a_s;
                when "000110" => -- srlv
                    result_s <= a_s;
                when "000111" => -- srav
                    result_s <= a_s;
                when "001000" => -- addi
                    result_s <= a_s + b_s;
                when "001001" => -- addiu

                    -- One important difference between addi and addiu is that 
                    -- addi will set the overflow flag if the result is too large to fit in the register, 
                    -- while addiu will not.

                    -- the name addiu is a misnomer, because it does not add unsigned integers, instead it adds signed integers.

                    result_s <= a_s + b_s; --TODO: dúvida, a e b são unsigned ou apenas b?

                when "001100" => -- andi
                    result_s <= a_s and b_s;
                when "001101" => -- ori
                    result_s <= a_s or b_s;
                when "001110" => -- xori
                    result_s <= a_s xor b_s;
                when "011000" => -- mult
                    result_s <= a_s * b_s;
                when "011001" => -- multu
                    result_s <= a_s * b_s;
                when "011010" => -- div
                    result_s <= a_s / b_s;
                when "011011" => -- divu
                    result_s <= a_s / b_s;
                when "100000" => -- add
                    result_s <= a_s + b_s;
                when "100001" => -- addu
                    -- See addiu comment
                    result_s <= a_s + b_s;

                when "100010" => -- sub
                    result_s <= a_s - b_s;
                when "100011" => -- subu
                    result_s <= a_s - b_s;
                when "100100" => -- and
                    result_s <= a_s and b_s;
                when "100101" => -- or
                    result_s <= a_s or b_s;
                when "100110" => -- xor
                    result_s <= a_s xor b_s;
                when "100111" => -- nor
                    result_s <= not(a_s or b_s);
                when others =>
                    result_s <= (others => '0');
            end case;

            if result_s = 0 then
                zero <= '1';
            else
                zero <= '0';
            end if;

            result <= std_logic_vector(result_s);
        end if;
    end process;
end rtl;

AluTb.vhdl

-- AluTb.vhdl
-- Author: Reinaldo Miranda de Assis
-- Date: 2023-04-21
-- Description: ALU Testbench

LIBRARY ieee;
USE ieee.std_logic_1164.ALL;
USE ieee.std_logic_unsigned.ALL;
USE IEEE.NUMERIC_STD.ALL;

-- Instruction	funccode/Function	
-- add 	    100000	
-- addu 	100001	
-- addi 	001000	
-- and 	    100100	
-- andi 	001100	
-- div 	    011010	
-- divu 	011011	 
-- mult 	011000	
-- multu 	011001	
-- nor 	    100111	
-- or 	    100101	
-- ori 	    001101	
-- sll 	    000000	
-- sllv 	000100	
-- sra 	    000011	
-- srav 	000111	
-- srl 	    000010	
-- srlv 	000110	
-- sub 	    100010	
-- subu 	100011	
-- xor 	    100110	
-- xori 	001110	

entity alutb is
end alutb;

architecture behavior of alutb is

    component alu is
        port (
            a, b : in std_logic_vector(31 downto 0);
            clk : in std_logic;
            func : in std_logic_vector(5 downto 0);
            shift : in std_logic_vector(4 downto 0);
            result : out std_logic_vector(31 downto 0);
            zero : out std_logic
        );
    end component alu;

    signal a, b : std_logic_vector(31 downto 0);
    signal func : std_logic_vector(5 downto 0);
    signal shift : std_logic_vector(4 downto 0);
    signal result : std_logic_vector(31 downto 0);
    signal zero : std_logic;
    signal clk : std_logic;

begin
    
        uut : alu port map (
            a => a,
            b => b,
            clk => clk,
            func => func,
            shift => shift,
            result => result,
            zero => zero
        );
    
        clk_process :process
        begin
                clk <= '0';
                wait for 10 ns;
                clk <= '1';
                wait for 10 ns;
        end process;

        process
        begin
            a <= "00000000000000000000000000000000";
            b <= "00000000000000000000000000000000";

            func <= "100000"; -- add

            wait for 100 ns;
            assert result = "00000000000000000000000000000000" report "add failed" severity error;
            assert zero = '1' report "add failed" severity error;

            a <= "00000000000000000000000000000001";
            b <= "00000000000000000000000000000001";
            func <= "100001"; -- addu
            wait for 100 ns;
            assert result = "00000000000000000000000000000010" report "addu failed" severity error;
            assert zero = '0' report "addu failed" severity error;

            a <= "00000000000000000000000000000001";
            b <= "11111111111111111111111111111111"; -- twos complement of 0x"00000001"
            func <= "100000"; -- add
            wait for 100 ns;
            assert result = "00000000000000000000000000000000" report "add failed" severity error;
            assert zero = '1' report "add failed" severity error;

            a <= "00000000000000000000000000000011";
            b <= "00000000000000000000000000000101";
            func <= "100010"; -- sub
            wait for 100 ns;
            assert result = "11111111111111111111111111111110" report "sub failed" severity error;
            assert zero = '0' report "sub failed" severity error;

            func <= "100100"; -- and
            wait for 100 ns;
            assert result = "00000000000000000000000000000001" report "and failed" severity error;
            assert zero = '0' report "and failed" severity error;

            func <= "100101"; -- or
            wait for 100 ns;
            assert result = "00000000000000000000000000000111" report "or failed" severity error;
            assert zero = '0' report "or failed" severity error;

            func <= "000000"; -- sll 
            shift <= "00001";
            wait for 100 ns;
            assert result = "00000000000000000000000000000110" report "sll failed" severity error;
            assert zero = '0' report "sll failed" severity error;

            func <= "000010"; -- srl
            wait for 100 ns;
            assert result = "00000000000000000000000000000001" report "srl failed" severity error;
            assert zero = '0' report "srl failed" severity error;

            wait;
        end process;
end;

wave.vcd
$date
  Sat Apr 22 20:25:20 2023
$end
$version
  GHDL v0
$end
$timescale
  1 fs
$end
$scope module standard $end
$upscope $end
$scope module textio $end
$upscope $end
$scope module std_logic_1164 $end
$upscope $end
$scope module std_logic_arith $end
$upscope $end
$scope module std_logic_unsigned $end
$upscope $end
$scope module numeric_std $end
$upscope $end
$scope module alutb $end
$var reg 32 ! a[31:0] $end
$var reg 32 " b[31:0] $end
$var reg 6 # func[5:0] $end
$var reg 5 $ shift[4:0] $end
$var reg 32 % result[31:0] $end
$var reg 1 & zero $end
$var reg 1 ' clk $end
$scope module uut $end
$var reg 32 ( a[31:0] $end
$var reg 32 ) b[31:0] $end
$var reg 1 * clk $end
$var reg 6 + func[5:0] $end
$var reg 5 , shift[4:0] $end
$var reg 32 - result[31:0] $end
$var reg 1 . zero $end
$var reg 32 / a_s[31:0] $end
$var reg 32 0 b_s[31:0] $end
$var reg 32 1 result_s[31:0] $end
$upscope $end
$upscope $end
$enddefinitions $end
#0
b00000000000000000000000000000000 !
b00000000000000000000000000000000 "
b100000 #
bUUUUU $
bUUUUUUUUUUUUUUUUUUUUUUUUUUUUUUUU %
U&
0'
b00000000000000000000000000000000 (
b00000000000000000000000000000000 )
0*
b100000 +
bUUUUU ,
bUUUUUUUUUUUUUUUUUUUUUUUUUUUUUUUU -
U.
b00000000000000000000000000000000 /
b00000000000000000000000000000000 0
bUUUUUUUUUUUUUUUUUUUUUUUUUUUUUUUU 1
#10000000
0&
1'
1*
0.
b00000000000000000000000000000000 1
#20000000
0'
0*
#30000000
b00000000000000000000000000000000 %
1&
1'
1*
b00000000000000000000000000000000 -
1.
#40000000
0'
0*
#50000000
1'
1*
#60000000
0'
0*
#70000000
1'
1*
#80000000
0'
0*
#90000000
1'
1*
#100000000
b00000000000000000000000000000001 !
b00000000000000000000000000000001 "
b100001 #
0'
b00000000000000000000000000000001 (
b00000000000000000000000000000001 )
0*
b100001 +
b00000000000000000000000000000001 /
b00000000000000000000000000000001 0
#110000000
1'
1*
b00000000000000000000000000000010 1
#120000000
0'
0*
#130000000
b00000000000000000000000000000010 %
0&
1'
1*
b00000000000000000000000000000010 -
0.
#140000000
0'
0*
#150000000
1'
1*
#160000000
0'
0*
#170000000
1'
1*
#180000000
0'
0*
#190000000
1'
1*
#200000000
b11111111111111111111111111111111 "
b100000 #
0'
b11111111111111111111111111111111 )
0*
b100000 +
b11111111111111111111111111111111 0
#210000000
1'
1*
b00000000000000000000000000000000 1
#220000000
0'
0*
#230000000
b00000000000000000000000000000000 %
1&
1'
1*
b00000000000000000000000000000000 -
1.
#240000000
0'
0*
#250000000
1'
1*
#260000000
0'
0*
#270000000
1'
1*
#280000000
0'
0*
#290000000
1'
1*
#300000000
b00000000000000000000000000000011 !
b00000000000000000000000000000101 "
b100010 #
0'
b00000000000000000000000000000011 (
b00000000000000000000000000000101 )
0*
b100010 +
b00000000000000000000000000000011 /
b00000000000000000000000000000101 0
#310000000
1'
1*
b11111111111111111111111111111110 1
#320000000
0'
0*
#330000000
b11111111111111111111111111111110 %
0&
1'
1*
b11111111111111111111111111111110 -
0.
#340000000
0'
0*
#350000000
1'
1*
#360000000
0'
0*
#370000000
1'
1*
#380000000
0'
0*
#390000000
1'
1*
#400000000
b100100 #
0'
0*
b100100 +
#410000000
1'
1*
b00000000000000000000000000000001 1
#420000000
0'
0*
#430000000
b00000000000000000000000000000001 %
1'
1*
b00000000000000000000000000000001 -
#440000000
0'
0*
#450000000
1'
1*
#460000000
0'
0*
#470000000
1'
1*
#480000000
0'
0*
#490000000
1'
1*
#500000000
b100101 #
0'
0*
b100101 +
#510000000
1'
1*
b00000000000000000000000000000111 1
#520000000
0'
0*
#530000000
b00000000000000000000000000000111 %
1'
1*
b00000000000000000000000000000111 -
#540000000
0'
0*
#550000000
1'
1*
#560000000
0'
0*
#570000000
1'
1*
#580000000
0'
0*
#590000000
1'
1*
#600000000
b000000 #
b00001 $
0'
0*
b000000 +
b00001 ,
#610000000
1'
1*
b00000000000000000000000000000110 1
#620000000
0'
0*
#630000000
b00000000000000000000000000000110 %
1'
1*
b00000000000000000000000000000110 -
#640000000
0'
0*
#650000000
1'
1*
#660000000
0'
0*
#670000000
1'
1*
#680000000
0'
0*
#690000000
1'
1*
#700000000
b000010 #
0'
0*
b000010 +
#710000000
1'
1*
b00000000000000000000000000000001 1
#720000000
0'
0*
#730000000
b00000000000000000000000000000001 %
1'
1*
b00000000000000000000000000000001 -
